setup.py
ljf7_gmail/__init__.py
ljf7_gmail/math_utils.py
ljf7_gmail/spam.py
spammer7.egg-info/PKG-INFO
spammer7.egg-info/SOURCES.txt
spammer7.egg-info/dependency_links.txt
spammer7.egg-info/top_level.txt