Metadata-Version: 2.1
Name: spammer7
Version: 1.0.0
Summary: Math utilities with Fibonacci, factorial, and Gmail email sending functionality.
Author: Andy Woz
Classifier: Programming Language :: Python :: 3
Classifier: Operating System :: OS Independent
Requires-Python: >=3.6
